loss_fun_c.cpython-312-darwin.so
splinecalib/__init__.py
splinecalib/calib_utils.py
splinecalib/loss_fun_c.c
splinecalib/loss_fun_c.pyx
splinecalib/splinecalib.py
splinecalib/tests/__init__.py
splinecalib/tests/test_binary_datasets.py
splinecalib/tests/test_multiclass_datasets.py
splinecalib/tests/test_unity_prior.py
splinecalib/tests/data_for_tests/calibset_2dplanes_727_cb1.csv
splinecalib/tests/data_for_tests/calibset_2dplanes_727_cb2.csv
splinecalib/tests/data_for_tests/calibset_2dplanes_727_cb3.csv
splinecalib/tests/data_for_tests/calibset_2dplanes_727_rf.csv
splinecalib/tests/data_for_tests/calibset_airlines_42493_cb1.csv
splinecalib/tests/data_for_tests/calibset_airlines_42493_cb2.csv
splinecalib/tests/data_for_tests/calibset_airlines_42493_cb3.csv
splinecalib/tests/data_for_tests/calibset_airlines_42493_rf.csv
splinecalib/tests/data_for_tests/calibset_mozilla4_1046_cb1.csv
splinecalib/tests/data_for_tests/calibset_mozilla4_1046_cb2.csv
splinecalib/tests/data_for_tests/calibset_mozilla4_1046_cb3.csv
splinecalib/tests/data_for_tests/calibset_mozilla4_1046_rf.csv
splinecalib/tests/data_for_tests/mnist4_calib_set.csv
splinecalib/tests/data_for_tests/mnist4_test_set.csv
splinecalib/tests/data_for_tests/testset_2dplanes_727_cb1.csv
splinecalib/tests/data_for_tests/testset_2dplanes_727_cb2.csv
splinecalib/tests/data_for_tests/testset_2dplanes_727_cb3.csv
splinecalib/tests/data_for_tests/testset_2dplanes_727_rf.csv
splinecalib/tests/data_for_tests/testset_airlines_42493_cb1.csv
splinecalib/tests/data_for_tests/testset_airlines_42493_cb2.csv
splinecalib/tests/data_for_tests/testset_airlines_42493_cb3.csv
splinecalib/tests/data_for_tests/testset_airlines_42493_rf.csv
splinecalib/tests/data_for_tests/testset_mozilla4_1046_cb1.csv
splinecalib/tests/data_for_tests/testset_mozilla4_1046_cb2.csv
splinecalib/tests/data_for_tests/testset_mozilla4_1046_cb3.csv
splinecalib/tests/data_for_tests/testset_mozilla4_1046_rf.csv
splinecalib-0.0.12.dist-info/licenses/LICENSE
splinecalib-0.0.12.dist-info/METADATA
splinecalib-0.0.12.dist-info/WHEEL
splinecalib-0.0.12.dist-info/top_level.txt
splinecalib-0.0.12.dist-info/RECORD
