Metadata-Version: 2.4
Name: splinecalib
Version: 0.0.12
License-File: LICENSE
Requires-Dist: pandas>=1.3
Requires-Dist: numpy>=1.21
Requires-Dist: scipy>=1.6
Requires-Dist: matplotlib>=1.0
Requires-Dist: joblib>=0.14.1
Requires-Dist: ml_insights>=1.0.4
Provides-Extra: dev
Requires-Dist: Cython>=3.0.0; extra == "dev"
Requires-Dist: build; extra == "dev"
Requires-Dist: setuptools; extra == "dev"
Dynamic: license-file
